command_storage/__init__.py
command_storage/controller/__init__.py
command_storage/controller/app.py
command_storage/controller/config.py
command_storage/initializer.py
command_storage/models/__init__.py
command_storage/models/constants.py
command_storage/models/database/__init__.py
command_storage/models/database/db_models.py
command_storage/models/database/json_wrapper.py
command_storage/models/enums/__init__.py
command_storage/models/enums/arguments.py
command_storage/models/enums/error.py
command_storage/models/models/__init__.py
command_storage/models/models/argument.py
command_storage/models/models/error.py
command_storage/views/__init__.py
command_storage/views/_create_cli.py
command_storage/views/_delete_cli.py
command_storage/views/_read_cli.py
command_storage/views/_update_cli.py
command_storage/views/cli.py
command_storage-0.1.2.dist-info/LICENSE
command_storage-0.1.2.dist-info/METADATA
command_storage-0.1.2.dist-info/WHEEL
command_storage-0.1.2.dist-info/entry_points.txt
command_storage-0.1.2.dist-info/RECORD
