Metadata-Version: 2.1
Name: command-storage
Version: 0.1.2
Summary: A command line tool to store CLI commands for quick access and usage.
Author: Ashutosh
Author-email: 37182127+ashu-tosh-kumar@users.noreply.github.com
Requires-Python: >=3.9,<4.0
Classifier: Programming Language :: Python :: 3
Classifier: Programming Language :: Python :: 3.9
Classifier: Programming Language :: Python :: 3.10
Classifier: Programming Language :: Python :: 3.11
Classifier: Programming Language :: Python :: 3.12
Requires-Dist: pydantic (>=2.6.3,<3.0.0)
Requires-Dist: pyperclip (>=1.8.2,<2.0.0)
Requires-Dist: shellingham (==1.4.0)
Requires-Dist: tabulate (>=0.9.0,<0.10.0)
Requires-Dist: thefuzz (>=0.22.1,<0.23.0)
Requires-Dist: typer (==0.7.0)
